columnclient/__init__.py
columnclient/client.py
columnclient/credentials.py
columnclient/runs.py
columnclient-0.1.0.dist-info/DESCRIPTION.rst
columnclient-0.1.0.dist-info/METADATA
columnclient-0.1.0.dist-info/RECORD
columnclient-0.1.0.dist-info/WHEEL
columnclient-0.1.0.dist-info/metadata.json
columnclient-0.1.0.dist-info/top_level.txt
tests/__init__.py
tests/test_client.py
tests/test_credentials.py
tests/test_runs.py
tests/utils.py
